{".class": "MypyFile", "_fullname": "11_args", "is_partial_stub_package": false, "is_stub": false, "names": {".class": "SymbolTable", "__doc__": {".class": "SymbolTableNode", "kind": "Gdef", "node": {".class": "Var", "flags": ["is_ready"], "fullname": "11_args.__doc__", "name": "__doc__", "type": "builtins.str"}}, "__file__": {".class": "SymbolTableNode", "kind": "Gdef", "node": {".class": "Var", "flags": ["is_ready"], "fullname": "11_args.__file__", "name": "__file__", "type": "builtins.str"}}, "__name__": {".class": "SymbolTableNode", "kind": "Gdef", "node": {".class": "Var", "flags": ["is_ready"], "fullname": "11_args.__name__", "name": "__name__", "type": "builtins.str"}}, "__package__": {".class": "SymbolTableNode", "kind": "Gdef", "node": {".class": "Var", "flags": ["is_ready"], "fullname": "11_args.__package__", "name": "__package__", "type": "builtins.str"}}, "a": {".class": "SymbolTableNode", "kind": "Gdef", "node": {".class": "Var", "flags": [], "fullname": "11_args.a", "name": "a", "type": {".class": "Instance", "args": ["builtins.int"], "type_ref": "builtins.list"}}}, "d": {".class": "SymbolTableNode", "kind": "Gdef", "node": {".class": "Var", "flags": [], "fullname": "11_args.d", "name": "d", "type": {".class": "Instance", "args": ["builtins.str", "builtins.object"], "type_ref": "builtins.dict"}}}, "f1": {".class": "SymbolTableNode", "kind": "Gdef", "node": {".class": "FuncDef", "arg_kinds": [0, 0], "arg_names": ["num1", "num2"], "flags": [], "fullname": "11_args.f1", "name": "f1", "type": null}}, "f2": {".class": "SymbolTableNode", "kind": "Gdef", "node": {".class": "FuncDef", "arg_kinds": [2], "arg_names": ["args"], "flags": [], "fullname": "11_args.f2", "name": "f2", "type": null}}, "f3": {".class": "SymbolTableNode", "kind": "Gdef", "node": {".class": "FuncDef", "arg_kinds": [0, 1], "arg_names": ["first", "second"], "flags": [], "fullname": "11_args.f3", "name": "f3", "type": null}}, "f4": {".class": "SymbolTableNode", "kind": "Gdef", "node": {".class": "FuncDef", "arg_kinds": [4], "arg_names": ["kwargs"], "flags": [], "fullname": "11_args.f4", "name": "f4", "type": null}}}, "path": "c:\\Users\\Richard\\Lambda Projects\\Intro-Python-I\\src\\11_args.py"}